<!DOCTYPE ui:UiBinder SYSTEM "http://dl.google.com/gwt/DTD/xhtml.ent">
<ui:UiBinder xmlns:ui="urn:ui:com.google.gwt.uibinder"
	xmlns:g="urn:import:com.google.gwt.user.client.ui">
	<ui:style>
		/* Add CSS here. See the GWT docs on UI Binder for more details */
		.important {
			font-weight: bold;
		}
	</ui:style>
	
	<g:DockLayoutPanel unit='EM'>
		<g:north size='4'>
			<g:Label>e School Management System</g:Label>
		</g:north>
		
		<g:west size='16'>
			<g:HTML>
				<ul>
					<li>Link 1</li>
					<li>Link 2</li>
				</ul>
			</g:HTML>
		</g:west>
		
		<g:center>
			<g:LayoutPanel ui:field="content" />
		</g:center>
	<!-- 	
		<g:south size='4'>
			<g:Label>footer</g:Label>
		</g:south>
	-->
	</g:DockLayoutPanel>
</ui:UiBinder> 